{"evs":[83,53,9,136,212,17],"wins":[{"opponent":"Charizard","move":{"category":"special move","defenderName":"Charizard","defenderHp":153,"movePct":1.13,"name":"Water Spout","totalDmg":173,"evs":[80,143,48,65,130,44]},"evs":[80,143,48,65,130,44]},{"opponent":"Charmander","move":{"category":"special move","defenderName":"Charmander","defenderHp":114,"movePct":2.25,"name":"Water Spout","totalDmg":257},"evs":[0,0,0,0,0,0]},{"opponent":"Charmeleon","move":{"category":"special move","defenderName":"Charmeleon","defenderHp":133,"movePct":1.6,"name":"Water Spout","totalDmg":213,"evs":[118,107,95,21,35,134]},"evs":[118,107,95,21,35,134]},{"opponent":"Squirtle","move":{"category":"physical move","defenderName":"Squirtle","defenderHp":119,"movePct":0.52,"name":"Mega Kick","totalDmg":62},"evs":[118,107,95,21,35,134]},{"opponent":"Caterpie","move":{"category":"special move","defenderName":"Caterpie","defenderHp":120,"movePct":1.86,"name":"Water Spout","totalDmg":223},"evs":[0,0,0,0,0,0]},{"opponent":"Metapod","move":{"category":"special move","defenderName":"Metapod","defenderHp":125,"movePct":1.58,"name":"Water Spout","totalDmg":198},"evs":[0,0,0,0,0,0]},{"opponent":"Butterfree","move":{"category":"physical move","defenderName":"Butterfree","defenderHp":135,"movePct":1.27,"name":"Rock Slide","totalDmg":171},"evs":[0,0,0,0,0,0]},{"opponent":"Clefairy","move":{"category":"physical move","defenderName":"Clefairy","defenderHp":145,"movePct":0.8,"name":"Iron Tail","totalDmg":116},"evs":[0,0,0,0,0,0]},{"opponent":"Vulpix","move":{"category":"special move","defenderName":"Vulpix","defenderHp":113,"movePct":1.88,"name":"Water Spout","totalDmg":213},"evs":[0,0,0,0,0,0]},{"opponent":"Ninetales","move":{"category":"special move","defenderName":"Ninetales","defenderHp":148,"movePct":1.03,"name":"Water Spout","totalDmg":152},"evs":[0,0,0,0,0,0]},{"opponent":"Diglett","move":{"category":"special move","defenderName":"Diglett","defenderHp":85,"movePct":3.25,"name":"Water Spout","totalDmg":276},"evs":[0,0,0,0,0,0]},{"opponent":"Dugtrio","move":{"category":"special move","defenderName":"Dugtrio","defenderHp":110,"movePct":1.83,"name":"Water Spout","totalDmg":201},"evs":[0,0,0,0,0,0]},{"opponent":"Meowth","move":{"category":"special move","defenderName":"Meowth","defenderHp":115,"movePct":1.39,"name":"Focus Blast","totalDmg":160},"evs":[0,0,0,0,0,0]},{"opponent":"Persian","move":{"category":"special move","defenderName":"Persian","defenderHp":140,"movePct":0.81,"name":"Focus Blast","totalDmg":114},"evs":[0,0,0,0,0,0]},{"opponent":"Growlithe","move":{"category":"special move","defenderName":"Growlithe","defenderHp":130,"movePct":1.98,"name":"Water Spout","totalDmg":257},"evs":[0,0,0,0,0,0]},{"opponent":"Arcanine","move":{"category":"special move","defenderName":"Arcanine","defenderHp":165,"movePct":1.1,"name":"Water Spout","totalDmg":181},"evs":[0,0,0,0,0,0]},{"opponent":"Machop","move":{"category":"special move","defenderName":"Machop","defenderHp":145,"movePct":1.12,"name":"Water Spout","totalDmg":163},"evs":[0,0,0,0,0,0]},{"opponent":"Machoke","move":{"category":"special move","defenderName":"Machoke","defenderHp":155,"movePct":0.72,"name":"Water Spout","totalDmg":112,"evs":[78,64,123,6,106,133]},"evs":[78,64,123,6,106,133]},{"opponent":"Ponyta","move":{"category":"special move","defenderName":"Ponyta","defenderHp":125,"movePct":1.7,"name":"Water Spout","totalDmg":213},"evs":[0,0,0,0,0,0]},{"opponent":"Rapidash","move":{"category":"special move","defenderName":"Rapidash","defenderHp":140,"movePct":1.29,"name":"Water Spout","totalDmg":181,"evs":[118,127,221,3,25,16]},"evs":[118,127,221,3,25,16]},{"opponent":"Farfetch'd","move":{"category":"special move","defenderName":"Farfetch'd","defenderHp":127,"movePct":0.87,"name":"Water Spout","totalDmg":110},"evs":[118,127,221,3,25,16]},{"opponent":"Shellder","move":{"category":"special move","defenderName":"Shellder","defenderHp":105,"movePct":1.01,"name":"Focus Blast","totalDmg":106},"evs":[118,127,221,3,25,16]},{"opponent":"Cloyster","move":{"category":"special move","defenderName":"Cloyster","defenderHp":125,"movePct":1.18,"name":"Focus Blast","totalDmg":148},"evs":[118,127,221,3,25,16]},{"opponent":"Gastly","move":{"category":"physical move","defenderName":"Gastly","defenderHp":105,"movePct":1.72,"name":"Earthquake","totalDmg":181,"evs":[55,104,114,97,8,132]},"evs":[55,104,114,97,8,132]},{"opponent":"Onix","move":{"category":"special move","defenderName":"Onix","defenderHp":110,"movePct":5.03,"name":"Water Spout","totalDmg":553},"evs":[0,0,0,0,0,0]},{"opponent":"Krabby","move":{"category":"special move","defenderName":"Krabby","defenderHp":105,"movePct":1.01,"name":"Focus Blast","totalDmg":106},"evs":[0,0,0,0,0,0]},{"opponent":"Kingler","move":{"category":"special move","defenderName":"Kingler","defenderHp":130,"movePct":0.53,"name":"Focus Blast","totalDmg":69},"evs":[0,0,0,0,0,0]},{"opponent":"Koffing","move":{"category":"special move","defenderName":"Koffing","defenderHp":115,"movePct":1.2,"name":"Water Spout","totalDmg":138},"evs":[0,0,0,0,0,0]},{"opponent":"Rhyhorn","move":{"category":"special move","defenderName":"Rhyhorn","defenderHp":155,"movePct":4.63,"name":"Water Spout","totalDmg":717},"evs":[0,0,0,0,0,0]},{"opponent":"Rhydon","move":{"category":"special move","defenderName":"Rhydon","defenderHp":180,"movePct":3.07,"name":"Water Spout","totalDmg":553,"evs":[40,20,176,131,90,53]},"evs":[40,20,176,131,90,53]},{"opponent":"Goldeen","move":{"category":"special move","defenderName":"Goldeen","defenderHp":120,"movePct":0.66,"name":"Focus Blast","totalDmg":79},"evs":[40,20,176,131,90,53]},{"opponent":"Magikarp","move":{"category":"special move","defenderName":"Magikarp","defenderHp":95,"movePct":1.25,"name":"Focus Blast","totalDmg":119,"evs":[42,12,81,62,63,250]},"evs":[42,12,81,62,63,250]},{"opponent":"Eevee","move":{"category":"special move","defenderName":"Eevee","defenderHp":130,"movePct":0.88,"name":"Focus Blast","totalDmg":114},"evs":[0,0,0,0,0,0]},{"opponent":"Jolteon","move":{"category":"physical move","defenderName":"Jolteon","defenderHp":140,"movePct":0.71,"name":"Earthquake","totalDmg":99},"evs":[0,0,0,0,0,0]},{"opponent":"Flareon","move":{"category":"special move","defenderName":"Flareon","defenderHp":140,"movePct":1.01,"name":"Water Spout","totalDmg":141},"evs":[0,0,0,0,0,0]},{"opponent":"Hoothoot","move":{"category":"special move","defenderName":"Hoothoot","defenderHp":135,"movePct":0.87,"name":"Water Spout","totalDmg":118},"evs":[0,0,0,0,0,0]},{"opponent":"Noctowl","move":{"category":"physical move","defenderName":"Noctowl","defenderHp":175,"movePct":0.49,"name":"Ice Punch","totalDmg":85,"evs":[116,120,20,78,151,25]},"evs":[116,120,20,78,151,25]},{"opponent":"Chinchou","move":{"category":"physical move","defenderName":"Chinchou","defenderHp":150,"movePct":1.03,"name":"Earthquake","totalDmg":155},"evs":[116,120,20,78,151,25]},{"opponent":"Pichu","move":{"category":"physical move","defenderName":"Pichu","defenderHp":95,"movePct":2.35,"name":"Earthquake","totalDmg":223},"evs":[0,0,0,0,0,0]},{"opponent":"Cleffa","move":{"category":"physical move","defenderName":"Cleffa","defenderHp":125,"movePct":1.3,"name":"Iron Tail","totalDmg":163},"evs":[0,0,0,0,0,0]},{"opponent":"Togepi","move":{"category":"special move","defenderName":"Togepi","defenderHp":110,"movePct":0.96,"name":"Water Spout","totalDmg":106},"evs":[0,0,0,0,0,0]},{"opponent":"Togetic","move":{"category":"physical move","defenderName":"Togetic","defenderHp":130,"movePct":0.58,"name":"Iron Tail","totalDmg":76},"evs":[0,0,0,0,0,0]},{"opponent":"Natu","move":{"category":"special move","defenderName":"Natu","defenderHp":115,"movePct":1.2,"name":"Water Spout","totalDmg":138},"evs":[0,0,0,0,0,0]},{"opponent":"Xatu","move":{"category":"special move","defenderName":"Xatu","defenderHp":140,"movePct":0.71,"name":"Water Spout","totalDmg":100},"evs":[0,0,0,0,0,0]},{"opponent":"Sudowoodo","move":{"category":"special move","defenderName":"Sudowoodo","defenderHp":145,"movePct":1.47,"name":"Water Spout","totalDmg":213},"evs":[0,0,0,0,0,0]},{"opponent":"Wooper","move":{"category":"special move","defenderName":"Wooper","defenderHp":130,"movePct":1.52,"name":"Water Spout","totalDmg":198},"evs":[0,0,0,0,0,0]},{"opponent":"Quagsire","move":{"category":"special move","defenderName":"Quagsire","defenderHp":170,"movePct":0.62,"name":"Water Spout","totalDmg":106},"evs":[0,0,0,0,0,0]},{"opponent":"Espeon","move":{"category":"physical move","defenderName":"Espeon","defenderHp":140,"movePct":0.57,"name":"Crunch","totalDmg":80},"evs":[0,0,0,0,0,0]},{"opponent":"Steelix","move":{"category":"special move","defenderName":"Steelix","defenderHp":150,"movePct":1.42,"name":"Water Spout","totalDmg":213},"evs":[0,0,0,0,0,0]},{"opponent":"Qwilfish","move":{"category":"physical move","defenderName":"Qwilfish","defenderHp":140,"movePct":0.54,"name":"Earthquake","totalDmg":76,"evs":[228,52,41,75,19,95]},"evs":[228,52,41,75,19,95]},{"opponent":"Shuckle","move":{"category":"special move","defenderName":"Shuckle","defenderHp":95,"movePct":0.85,"name":"Water Spout","totalDmg":81},"evs":[228,52,41,75,19,95]},{"opponent":"Sneasel","move":{"category":"special move","defenderName":"Sneasel","defenderHp":130,"movePct":1.71,"name":"Focus Blast","totalDmg":222},"evs":[0,0,0,0,0,0]},{"opponent":"Swinub","move":{"category":"special move","defenderName":"Swinub","defenderHp":125,"movePct":2.86,"name":"Water Spout","totalDmg":358},"evs":[0,0,0,0,0,0]},{"opponent":"Piloswine","move":{"category":"special move","defenderName":"Piloswine","defenderHp":175,"movePct":1.29,"name":"Water Spout","totalDmg":225},"evs":[0,0,0,0,0,0]},{"opponent":"Corsola","move":{"category":"special move","defenderName":"Corsola","defenderHp":140,"movePct":0.61,"name":"Focus Blast","totalDmg":85},"evs":[0,0,0,0,0,0]},{"opponent":"Remoraid","move":{"category":"special move","defenderName":"Remoraid","defenderHp":110,"movePct":0.79,"name":"Focus Blast","totalDmg":87},"evs":[0,0,0,0,0,0]},{"opponent":"Delibird","move":{"category":"physical move","defenderName":"Delibird","defenderHp":120,"movePct":1.73,"name":"Rock Slide","totalDmg":208},"evs":[50,110,220,50,74,6]},{"opponent":"Tyrogue","move":{"category":"special move","defenderName":"Tyrogue","defenderHp":110,"movePct":1.48,"name":"Water Spout","totalDmg":163},"evs":[0,0,0,0,0,0]},{"opponent":"Hitmontop","move":{"category":"special move","defenderName":"Hitmontop","defenderHp":125,"movePct":0.56,"name":"Water Spout","totalDmg":70,"evs":[77,112,150,163,3,5]},"evs":[77,112,150,163,3,5]},{"opponent":"Larvitar","move":{"category":"special move","defenderName":"Larvitar","defenderHp":125,"movePct":4.89,"name":"Water Spout","totalDmg":611},"evs":[77,112,150,163,3,5]},{"opponent":"Pupitar","move":{"category":"special move","defenderName":"Pupitar","defenderHp":145,"movePct":3.29,"name":"Water Spout","totalDmg":477},"evs":[77,112,150,163,3,5]},{"opponent":"Tyranitar","move":{"category":"special move","defenderName":"Tyranitar","defenderHp":175,"movePct":1.1,"name":"Focus Blast","totalDmg":193},"evs":[0,0,0,0,0,0]},{"opponent":"Zigzagoon","move":{"category":"special move","defenderName":"Zigzagoon","defenderHp":113,"movePct":1.39,"name":"Focus Blast","totalDmg":157},"evs":[0,0,0,0,0,0]},{"opponent":"Linoone","move":{"category":"special move","defenderName":"Linoone","defenderHp":153,"movePct":0.78,"name":"Focus Blast","totalDmg":119},"evs":[0,0,0,0,0,0]},{"opponent":"Lotad","move":{"category":"physical move","defenderName":"Lotad","defenderHp":115,"movePct":0.82,"name":"Mega Kick","totalDmg":94},"evs":[0,0,0,0,0,0]},{"opponent":"Lombre","move":{"category":"physical move","defenderName":"Lombre","defenderHp":135,"movePct":0.5,"name":"Mega Kick","totalDmg":67,"evs":[27,51,30,89,220,93]},"evs":[27,51,30,89,220,93]},{"opponent":"Seedot","move":{"category":"special move","defenderName":"Seedot","defenderHp":115,"movePct":1.53,"name":"Blizzard","totalDmg":176},"evs":[0,0,0,0,0,0]},{"opponent":"Nuzleaf","move":{"category":"special move","defenderName":"Nuzleaf","defenderHp":145,"movePct":1.1,"name":"Focus Blast","totalDmg":160},"evs":[0,0,0,0,0,0]},{"opponent":"Wingull","move":{"category":"physical move","defenderName":"Wingull","defenderHp":115,"movePct":1.03,"name":"Rock Slide","totalDmg":118},"evs":[0,0,0,0,0,0]},{"opponent":"Ralts","move":{"category":"physical move","defenderName":"Ralts","defenderHp":103,"movePct":1.69,"name":"Iron Tail","totalDmg":174},"evs":[0,0,0,0,0,0]},{"opponent":"Kirlia","move":{"category":"physical move","defenderName":"Kirlia","defenderHp":113,"movePct":1.27,"name":"Iron Tail","totalDmg":143},"evs":[0,0,0,0,0,0]},{"opponent":"Gardevoir","move":{"category":"physical move","defenderName":"Gardevoir","defenderHp":143,"movePct":0.66,"name":"Iron Tail","totalDmg":94,"evs":[87,99,87,13,215,9]},"evs":[87,99,87,13,215,9]},{"opponent":"Nincada","move":{"category":"special move","defenderName":"Nincada","defenderHp":106,"movePct":3.44,"name":"Water Spout","totalDmg":365},"evs":[87,99,87,13,215,9]},{"opponent":"Ninjask","move":{"category":"physical move","defenderName":"Ninjask","defenderHp":136,"movePct":1.51,"name":"Rock Slide","totalDmg":205},"evs":[0,0,0,0,0,0]},{"opponent":"Shedinja","move":{"category":"special move","defenderName":"Shedinja","defenderHp":76,"movePct":2.36,"name":"Water Spout","totalDmg":179},"evs":[0,0,0,0,0,0]},{"opponent":"Sableye","move":{"category":"special move","defenderName":"Sableye","defenderHp":125,"movePct":0.85,"name":"Water Spout","totalDmg":106},"evs":[0,0,0,0,0,0]},{"opponent":"Mawile","move":{"category":"special move","defenderName":"Mawile","defenderHp":125,"movePct":0.96,"name":"Water Spout","totalDmg":120},"evs":[0,0,0,0,0,0]},{"opponent":"Electrike","move":{"category":"special move","defenderName":"Electrike","defenderHp":115,"movePct":1.3,"name":"Water Spout","totalDmg":149},"evs":[0,0,0,0,0,0]},{"opponent":"Torkoal","move":{"category":"special move","defenderName":"Torkoal","defenderHp":145,"movePct":1.39,"name":"Water Spout","totalDmg":201},"evs":[0,0,0,0,0,0]},{"opponent":"Trapinch","move":{"category":"special move","defenderName":"Trapinch","defenderHp":120,"movePct":2.3,"name":"Water Spout","totalDmg":276},"evs":[0,0,0,0,0,0]},{"opponent":"Vibrava","move":{"category":"special move","defenderName":"Vibrava","defenderHp":125,"movePct":2.02,"name":"Blizzard","totalDmg":253},"evs":[0,0,0,0,0,0]},{"opponent":"Flygon","move":{"category":"special move","defenderName":"Flygon","defenderHp":155,"movePct":1.15,"name":"Blizzard","totalDmg":179,"evs":[22,39,11,64,168,206]},"evs":[0,0,0,0,0,0]},{"opponent":"Lunatone","move":{"category":"special move","defenderName":"Lunatone","defenderHp":165,"movePct":1.05,"name":"Water Spout","totalDmg":173},"evs":[0,0,0,0,0,0]},{"opponent":"Solrock","move":{"category":"special move","defenderName":"Solrock","defenderHp":165,"movePct":1.29,"name":"Water Spout","totalDmg":213},"evs":[0,0,0,0,0,0]},{"opponent":"Barboach","move":{"category":"special move","defenderName":"Barboach","defenderHp":125,"movePct":1.18,"name":"Water Spout","totalDmg":147},"evs":[0,0,0,0,0,0]},{"opponent":"Whiscash","move":{"category":"special move","defenderName":"Whiscash","defenderHp":185,"movePct":0.54,"name":"Water Spout","totalDmg":99},"evs":[0,0,0,0,0,0]},{"opponent":"Corphish","move":{"category":"special move","defenderName":"Corphish","defenderHp":118,"movePct":0.74,"name":"Focus Blast","totalDmg":87},"evs":[0,0,0,0,0,0]},{"opponent":"Crawdaunt","move":{"category":"special move","defenderName":"Crawdaunt","defenderHp":138,"movePct":0.93,"name":"Focus Blast","totalDmg":129},"evs":[0,0,0,0,0,0]},{"opponent":"Baltoy","move":{"category":"special move","defenderName":"Baltoy","defenderHp":115,"movePct":1.75,"name":"Water Spout","totalDmg":201},"evs":[0,0,0,0,0,0]},{"opponent":"Feebas","move":{"category":"physical move","defenderName":"Feebas","defenderHp":95,"movePct":1.23,"name":"Mega Kick","totalDmg":117,"evs":[67,61,56,111,134,81]},"evs":[67,61,56,111,134,81]},{"opponent":"Duskull","move":{"category":"special move","defenderName":"Duskull","defenderHp":95,"movePct":0.86,"name":"Water Spout","totalDmg":82},"evs":[0,0,0,0,0,0]},{"opponent":"Dusclops","move":{"category":"special move","defenderName":"Dusclops","defenderHp":115,"movePct":0.53,"name":"Water Spout","totalDmg":61},"evs":[0,0,0,0,0,0]},{"opponent":"Snorunt","move":{"category":"special move","defenderName":"Snorunt","defenderHp":125,"movePct":1.1,"name":"Focus Blast","totalDmg":138},"evs":[0,0,0,0,0,0]},{"opponent":"Glalie","move":{"category":"special move","defenderName":"Glalie","defenderHp":155,"movePct":0.63,"name":"Focus Blast","totalDmg":97,"evs":[225,44,20,61,26,134]},"evs":[225,44,20,61,26,134]},{"opponent":"Budew","move":{"category":"physical move","defenderName":"Budew","defenderHp":115,"movePct":1,"name":"Zen Headbutt","totalDmg":115},"evs":[0,0,0,0,0,0]},{"opponent":"Combee","move":{"category":"physical move","defenderName":"Combee","defenderHp":105,"movePct":1.84,"name":"Rock Slide","totalDmg":193},"evs":[0,0,0,0,0,0]},{"opponent":"Vespiquen","move":{"category":"physical move","defenderName":"Vespiquen","defenderHp":145,"movePct":0.7,"name":"Rock Slide","totalDmg":101},"evs":[0,0,0,0,0,0]},{"opponent":"Cherubi","move":{"category":"special move","defenderName":"Cherubi","defenderHp":120,"movePct":1.01,"name":"Blizzard","totalDmg":121,"evs":[80,87,40,17,172,114]},"evs":[80,87,40,17,172,114]},{"opponent":"Shellos","move":{"category":"physical move","defenderName":"Shellos","defenderHp":151,"movePct":0.46,"name":"Mega Kick","totalDmg":69,"evs":[201,139,132,26,7,5]},"evs":[201,139,132,26,7,5]},{"opponent":"Drifloon","move":{"category":"special move","defenderName":"Drifloon","defenderHp":165,"movePct":0.85,"name":"Water Spout","totalDmg":140},"evs":[0,0,0,0,0,0]},{"opponent":"Stunky","move":{"category":"special move","defenderName":"Stunky","defenderHp":138,"movePct":1.07,"name":"Water Spout","totalDmg":147},"evs":[0,0,0,0,0,0]},{"opponent":"Skuntank","move":{"category":"special move","defenderName":"Skuntank","defenderHp":178,"movePct":0.62,"name":"Water Spout","totalDmg":111,"evs":[159,26,28,130,48,119]},"evs":[159,26,28,130,48,119]},{"opponent":"Bronzor","move":{"category":"special move","defenderName":"Bronzor","defenderHp":132,"movePct":0.74,"name":"Water Spout","totalDmg":98},"evs":[159,26,28,130,48,119]},{"opponent":"Bronzong","move":{"category":"special move","defenderName":"Bronzong","defenderHp":142,"movePct":0.54,"name":"Water Spout","totalDmg":77},"evs":[159,26,28,130,48,119]},{"opponent":"Bonsly","move":{"category":"special move","defenderName":"Bonsly","defenderHp":125,"movePct":2.54,"name":"Water Spout","totalDmg":318},"evs":[159,26,28,130,48,119]},{"opponent":"Mime Jr.","move":{"category":"physical move","defenderName":"Mime Jr.","defenderHp":95,"movePct":1.32,"name":"Iron Tail","totalDmg":125},"evs":[159,26,28,130,48,119]},{"opponent":"Riolu","move":{"category":"special move","defenderName":"Riolu","defenderHp":115,"movePct":1.3,"name":"Water Spout","totalDmg":149},"evs":[0,0,0,0,0,0]},{"opponent":"Hippopotas","move":{"category":"special move","defenderName":"Hippopotas","defenderHp":143,"movePct":2.03,"name":"Water Spout","totalDmg":290},"evs":[0,0,0,0,0,0]},{"opponent":"Hippowdon","move":{"category":"special move","defenderName":"Hippowdon","defenderHp":183,"movePct":1.08,"name":"Water Spout","totalDmg":197},"evs":[0,0,0,0,0,0]},{"opponent":"Skorupi","move":{"category":"special move","defenderName":"Skorupi","defenderHp":115,"movePct":1.04,"name":"Water Spout","totalDmg":120},"evs":[0,0,0,0,0,0]},{"opponent":"Drapion","move":{"category":"special move","defenderName":"Drapion","defenderHp":145,"movePct":0.66,"name":"Water Spout","totalDmg":95},"evs":[0,0,0,0,0,0]},{"opponent":"Croagunk","move":{"category":"physical move","defenderName":"Croagunk","defenderHp":123,"movePct":1.72,"name":"Zen Headbutt","totalDmg":212},"evs":[0,0,0,0,0,0]},{"opponent":"Toxicroak","move":{"category":"physical move","defenderName":"Toxicroak","defenderHp":158,"movePct":0.96,"name":"Zen Headbutt","totalDmg":151,"evs":[26,41,184,181,75,3]},"evs":[26,41,184,181,75,3]},{"opponent":"Mantyke","move":{"category":"physical move","defenderName":"Mantyke","defenderHp":120,"movePct":0.74,"name":"Rock Slide","totalDmg":89},"evs":[26,41,184,181,75,3]},{"opponent":"Snover","move":{"category":"special move","defenderName":"Snover","defenderHp":135,"movePct":1.09,"name":"Focus Blast","totalDmg":147},"evs":[0,0,0,0,0,0]},{"opponent":"Weavile","move":{"category":"special move","defenderName":"Weavile","defenderHp":145,"movePct":1.28,"name":"Focus Blast","totalDmg":186},"evs":[0,0,0,0,0,0]},{"opponent":"Rhyperior","move":{"category":"special move","defenderName":"Rhyperior","defenderHp":190,"movePct":2.53,"name":"Water Spout","totalDmg":481,"evs":[115,34,100,163,95,3]},"evs":[115,34,100,163,95,3]},{"opponent":"Togekiss","move":{"category":"special move","defenderName":"Togekiss","defenderHp":160,"movePct":0.5,"name":"Water Spout","totalDmg":80,"evs":[9,160,12,70,42,217]},"evs":[9,160,12,70,42,217]},{"opponent":"Leafeon","move":{"category":"special move","defenderName":"Leafeon","defenderHp":140,"movePct":0.81,"name":"Blizzard","totalDmg":113},"evs":[9,160,12,70,42,217]},{"opponent":"Glaceon","move":{"category":"special move","defenderName":"Glaceon","defenderHp":140,"movePct":0.66,"name":"Focus Blast","totalDmg":92},"evs":[9,160,12,70,42,217]},{"opponent":"Mamoswine","move":{"category":"special move","defenderName":"Mamoswine","defenderHp":185,"movePct":1.32,"name":"Water Spout","totalDmg":244},"evs":[9,160,12,70,42,217]},{"opponent":"Froslass","move":{"category":"special move","defenderName":"Froslass","defenderHp":145,"movePct":0.69,"name":"Water Spout","totalDmg":100,"evs":[128,12,110,110,50,100]},"evs":[128,12,110,110,50,100]},{"opponent":"Purrloin","move":{"category":"special move","defenderName":"Purrloin","defenderHp":116,"movePct":1.45,"name":"Focus Blast","totalDmg":168},"evs":[0,0,0,0,0,0]},{"opponent":"Liepard","move":{"category":"special move","defenderName":"Liepard","defenderHp":139,"movePct":0.99,"name":"Focus Blast","totalDmg":138},"evs":[0,0,0,0,0,0]},{"opponent":"Munna","move":{"category":"special move","defenderName":"Munna","defenderHp":151,"movePct":0.79,"name":"Water Spout","totalDmg":120},"evs":[0,0,0,0,0,0]},{"opponent":"Pidove","move":{"category":"special move","defenderName":"Pidove","defenderHp":125,"movePct":1.57,"name":"Water Spout","totalDmg":196},"evs":[74,61,27,77,219,52]},{"opponent":"Tranquill","move":{"category":"special move","defenderName":"Tranquill","defenderHp":137,"movePct":1.15,"name":"Water Spout","totalDmg":158},"evs":[74,61,27,77,219,52]},{"opponent":"Roggenrola","move":{"category":"special move","defenderName":"Roggenrola","defenderHp":130,"movePct":3.05,"name":"Water Spout","totalDmg":397,"evs":[169,137,63,94,19,28]},"evs":[169,137,63,94,19,28]},{"opponent":"Boldore","move":{"category":"special move","defenderName":"Boldore","defenderHp":145,"movePct":2.3,"name":"Water Spout","totalDmg":333},"evs":[169,137,63,94,19,28]},{"opponent":"Gigalith","move":{"category":"special move","defenderName":"Gigalith","defenderHp":160,"movePct":1.26,"name":"Water Spout","totalDmg":202},"evs":[169,137,63,94,19,28]},{"opponent":"Woobat","move":{"category":"special move","defenderName":"Woobat","defenderHp":140,"movePct":1.13,"name":"Water Spout","totalDmg":158},"evs":[169,137,63,94,19,28]},{"opponent":"Swoobat","move":{"category":"special move","defenderName":"Swoobat","defenderHp":142,"movePct":0.94,"name":"Water Spout","totalDmg":133},"evs":[0,0,0,0,0,0]},{"opponent":"Drilbur","move":{"category":"special move","defenderName":"Drilbur","defenderHp":135,"movePct":2.04,"name":"Water Spout","totalDmg":276},"evs":[0,0,0,0,0,0]},{"opponent":"Excadrill","move":{"category":"special move","defenderName":"Excadrill","defenderHp":185,"movePct":1.15,"name":"Water Spout","totalDmg":213,"evs":[156,6,29,45,220,54]},"evs":[156,6,29,45,220,54]},{"opponent":"Timburr","move":{"category":"special move","defenderName":"Timburr","defenderHp":150,"movePct":1.15,"name":"Water Spout","totalDmg":172},"evs":[156,6,29,45,220,54]},{"opponent":"Gurdurr","move":{"category":"special move","defenderName":"Gurdurr","defenderHp":160,"movePct":0.84,"name":"Water Spout","totalDmg":135},"evs":[156,6,29,45,220,54]},{"opponent":"Conkeldurr","move":{"category":"special move","defenderName":"Conkeldurr","defenderHp":180,"movePct":0.62,"name":"Water Spout","totalDmg":112},"evs":[156,6,29,45,220,54]},{"opponent":"Tympole","move":{"category":"special move","defenderName":"Tympole","defenderHp":125,"movePct":0.67,"name":"Focus Blast","totalDmg":84},"evs":[156,6,29,45,220,54]},{"opponent":"Palpitoad","move":{"category":"special move","defenderName":"Palpitoad","defenderHp":150,"movePct":0.85,"name":"Water Spout","totalDmg":127},"evs":[156,6,29,45,220,54]},{"opponent":"Seismitoad","move":{"category":"special move","defenderName":"Seismitoad","defenderHp":180,"movePct":0.56,"name":"Water Spout","totalDmg":100},"evs":[156,6,29,45,220,54]},{"opponent":"Cottonee","move":{"category":"special move","defenderName":"Cottonee","defenderHp":115,"movePct":1.1,"name":"Blizzard","totalDmg":126},"evs":[0,0,0,0,0,0]},{"opponent":"Basculin","move":{"category":"special move","defenderName":"Basculin","defenderHp":145,"movePct":0.44,"name":"Focus Blast","totalDmg":64,"evs":[179,80,1,161,57,32]},"evs":[179,80,1,161,57,32]},{"opponent":"Darumaka","move":{"category":"special move","defenderName":"Darumaka","defenderHp":145,"movePct":2.26,"name":"Water Spout","totalDmg":328},"evs":[179,80,1,161,57,32]},{"opponent":"Darmanitan","move":{"category":"special move","defenderName":"Darmanitan","defenderHp":180,"movePct":1.58,"name":"Water Spout","totalDmg":285,"evs":[115,98,79,122,80,16]},"evs":[115,98,79,122,80,16]},{"opponent":"Dwebble","move":{"category":"special move","defenderName":"Dwebble","defenderHp":125,"movePct":2.61,"name":"Water Spout","totalDmg":326},"evs":[0,0,0,0,0,0]},{"opponent":"Crustle","move":{"category":"special move","defenderName":"Crustle","defenderHp":145,"movePct":1.32,"name":"Water Spout","totalDmg":191},"evs":[0,0,0,0,0,0]},{"opponent":"Scraggy","move":{"category":"special move","defenderName":"Scraggy","defenderHp":125,"movePct":0.86,"name":"Focus Blast","totalDmg":108},"evs":[0,0,0,0,0,0]},{"opponent":"Scrafty","move":{"category":"special move","defenderName":"Scrafty","defenderHp":140,"movePct":0.52,"name":"Focus Blast","totalDmg":73},"evs":[0,0,0,0,0,0]},{"opponent":"Yamask","move":{"category":"special move","defenderName":"Yamask","defenderHp":113,"movePct":0.94,"name":"Water Spout","totalDmg":106},"evs":[0,0,0,0,0,0]},{"opponent":"Cofagrigus","move":{"category":"special move","defenderName":"Cofagrigus","defenderHp":133,"movePct":0.55,"name":"Water Spout","totalDmg":73},"evs":[0,0,0,0,0,0]},{"opponent":"Trubbish","move":{"category":"special move","defenderName":"Trubbish","defenderHp":125,"movePct":0.88,"name":"Water Spout","totalDmg":110},"evs":[0,0,0,0,0,0]},{"opponent":"Minccino","move":{"category":"special move","defenderName":"Minccino","defenderHp":130,"movePct":1.23,"name":"Focus Blast","totalDmg":160},"evs":[0,0,0,0,0,0]},{"opponent":"Cinccino","move":{"category":"special move","defenderName":"Cinccino","defenderHp":150,"movePct":0.81,"name":"Focus Blast","totalDmg":121,"evs":[82,112,180,103,2,31]},"evs":[82,112,180,103,2,31]},{"opponent":"Gothita","move":{"category":"special move","defenderName":"Gothita","defenderHp":120,"movePct":0.99,"name":"Water Spout","totalDmg":119},"evs":[82,112,180,103,2,31]},{"opponent":"Gothorita","move":{"category":"special move","defenderName":"Gothorita","defenderHp":135,"movePct":0.72,"name":"Water Spout","totalDmg":97},"evs":[82,112,180,103,2,31]},{"opponent":"Gothitelle","move":{"category":"special move","defenderName":"Gothitelle","defenderHp":145,"movePct":0.54,"name":"Water Spout","totalDmg":78},"evs":[82,112,180,103,2,31]},{"opponent":"Solosis","move":{"category":"special move","defenderName":"Solosis","defenderHp":120,"movePct":1.2,"name":"Water Spout","totalDmg":144},"evs":[0,0,0,0,0,0]},{"opponent":"Vanillite","move":{"category":"special move","defenderName":"Vanillite","defenderHp":111,"movePct":1.09,"name":"Focus Blast","totalDmg":121},"evs":[0,0,0,0,0,0]},{"opponent":"Vanillish","move":{"category":"special move","defenderName":"Vanillish","defenderHp":126,"movePct":0.81,"name":"Focus Blast","totalDmg":102,"evs":[123,19,30,60,130,148]},"evs":[123,19,30,60,130,148]},{"opponent":"Karrablast","move":{"category":"special move","defenderName":"Karrablast","defenderHp":125,"movePct":1.1,"name":"Water Spout","totalDmg":138},"evs":[0,0,0,0,0,0]},{"opponent":"Frillish","move":{"category":"physical move","defenderName":"Frillish","defenderHp":130,"movePct":0.7,"name":"Crunch","totalDmg":91},"evs":[0,0,0,0,0,0]},{"opponent":"Joltik","move":{"category":"special move","defenderName":"Joltik","defenderHp":125,"movePct":1.02,"name":"Water Spout","totalDmg":128,"evs":[51,137,117,113,10,82]},"evs":[51,137,117,113,10,82]},{"opponent":"Ferroseed","move":{"category":"special move","defenderName":"Ferroseed","defenderHp":119,"movePct":0.77,"name":"Focus Blast","totalDmg":92},"evs":[0,0,0,0,0,0]},{"opponent":"Klink","move":{"category":"special move","defenderName":"Klink","defenderHp":115,"movePct":1.05,"name":"Focus Blast","totalDmg":121},"evs":[0,0,0,0,0,0]},{"opponent":"Klang","move":{"category":"special move","defenderName":"Klang","defenderHp":135,"movePct":0.69,"name":"Focus Blast","totalDmg":93,"evs":[109,139,74,167,16,5]},"evs":[109,139,74,167,16,5]},{"opponent":"Klinklang","move":{"category":"special move","defenderName":"Klinklang","defenderHp":135,"movePct":0.82,"name":"Focus Blast","totalDmg":111},"evs":[0,0,0,0,0,0]},{"opponent":"Elgyem","move":{"category":"special move","defenderName":"Elgyem","defenderHp":130,"movePct":0.92,"name":"Water Spout","totalDmg":120},"evs":[0,0,0,0,0,0]},{"opponent":"Litwick","move":{"category":"special move","defenderName":"Litwick","defenderHp":125,"movePct":1.92,"name":"Water Spout","totalDmg":240},"evs":[0,0,0,0,0,0]},{"opponent":"Lampent","move":{"category":"special move","defenderName":"Lampent","defenderHp":135,"movePct":1.67,"name":"Water Spout","totalDmg":225},"evs":[0,0,0,0,0,0]},{"opponent":"Chandelure","move":{"category":"special move","defenderName":"Chandelure","defenderHp":135,"movePct":1.22,"name":"Water Spout","totalDmg":165,"evs":[20,73,126,34,129,128]},"evs":[0,0,0,0,0,0]},{"opponent":"Axew","move":{"category":"special move","defenderName":"Axew","defenderHp":121,"movePct":1.21,"name":"Blizzard","totalDmg":147},"evs":[0,0,0,0,0,0]},{"opponent":"Fraxure","move":{"category":"special move","defenderName":"Fraxure","defenderHp":141,"movePct":0.89,"name":"Blizzard","totalDmg":126,"evs":[204,10,67,181,12,36]},"evs":[204,10,67,181,12,36]},{"opponent":"Cubchoo","move":{"category":"special move","defenderName":"Cubchoo","defenderHp":130,"movePct":1.23,"name":"Focus Blast","totalDmg":160},"evs":[0,0,0,0,0,0]},{"opponent":"Beartic","move":{"category":"special move","defenderName":"Beartic","defenderHp":170,"movePct":0.57,"name":"Focus Blast","totalDmg":97,"evs":[70,158,101,72,70,39]},"evs":[70,158,101,72,70,39]},{"opponent":"Golett","move":{"category":"special move","defenderName":"Golett","defenderHp":134,"movePct":1.92,"name":"Water Spout","totalDmg":257},"evs":[0,0,0,0,0,0]},{"opponent":"Golurk","move":{"category":"special move","defenderName":"Golurk","defenderHp":164,"movePct":1.1,"name":"Water Spout","totalDmg":181},"evs":[0,0,0,0,0,0]},{"opponent":"Pawniard","move":{"category":"special move","defenderName":"Pawniard","defenderHp":120,"movePct":2.67,"name":"Focus Blast","totalDmg":320},"evs":[0,0,0,0,0,0]},{"opponent":"Bisharp","move":{"category":"special move","defenderName":"Bisharp","defenderHp":140,"movePct":1.54,"name":"Focus Blast","totalDmg":216,"evs":[82,218,69,61,29,51]},"evs":[82,218,69,61,29,51]},{"opponent":"Rufflet","move":{"category":"special move","defenderName":"Rufflet","defenderHp":145,"movePct":0.95,"name":"Water Spout","totalDmg":138},"evs":[82,218,69,61,29,51]},{"opponent":"Vullaby","move":{"category":"special move","defenderName":"Vullaby","defenderHp":145,"movePct":0.73,"name":"Water Spout","totalDmg":106},"evs":[0,0,0,0,0,0]},{"opponent":"Heatmor","move":{"category":"special move","defenderName":"Heatmor","defenderHp":160,"movePct":1.31,"name":"Water Spout","totalDmg":210},"evs":[0,0,0,0,0,0]},{"opponent":"Durant","move":{"category":"special move","defenderName":"Durant","defenderHp":133,"movePct":0.99,"name":"Water Spout","totalDmg":132},"evs":[0,0,0,0,0,0]},{"opponent":"Deino","move":{"category":"special move","defenderName":"Deino","defenderHp":127,"movePct":1.09,"name":"Focus Blast","totalDmg":138},"evs":[0,0,0,0,0,0]},{"opponent":"Zweilous","move":{"category":"special move","defenderName":"Zweilous","defenderHp":147,"movePct":0.73,"name":"Focus Blast","totalDmg":108},"evs":[0,0,0,0,0,0]},{"opponent":"Hydreigon","move":{"category":"special move","defenderName":"Hydreigon","defenderHp":167,"movePct":0.53,"name":"Focus Blast","totalDmg":89,"evs":[242,52,115,7,42,52]},"evs":[242,52,115,7,42,52]},{"opponent":"Cobalion","move":{"category":"special move","defenderName":"Cobalion","defenderHp":166,"movePct":0.64,"name":"Focus Blast","totalDmg":106},"evs":[0,0,0,0,0,0]},{"opponent":"Kyurem","move":{"category":"special move","defenderName":"Kyurem","defenderHp":200,"movePct":0.45,"name":"Focus Blast","totalDmg":89,"evs":[79,5,20,141,110,155]},"evs":[79,5,20,141,110,155]},{"opponent":"Bunnelby","move":{"category":"special move","defenderName":"Bunnelby","defenderHp":113,"movePct":1.51,"name":"Focus Blast","totalDmg":171},"evs":[0,0,0,0,0,0]},{"opponent":"Diggersby","move":{"category":"special move","defenderName":"Diggersby","defenderHp":160,"movePct":1.17,"name":"Water Spout","totalDmg":187,"evs":[165,117,43,12,86,87]},"evs":[165,117,43,12,86,87]},{"opponent":"Pancham","move":{"category":"special move","defenderName":"Pancham","defenderHp":142,"movePct":0.94,"name":"Water Spout","totalDmg":134},"evs":[165,117,43,12,86,87]},{"opponent":"Espurr","move":{"category":"special move","defenderName":"Espurr","defenderHp":137,"movePct":0.82,"name":"Water Spout","totalDmg":112},"evs":[0,0,0,0,0,0]},{"opponent":"Meowstic","move":{"category":"special move","defenderName":"Meowstic","defenderHp":149,"movePct":0.6,"name":"Water Spout","totalDmg":90},"evs":[0,0,0,0,0,0]},{"opponent":"Honedge","move":{"category":"special move","defenderName":"Honedge","defenderHp":120,"movePct":1.31,"name":"Water Spout","totalDmg":157},"evs":[0,0,0,0,0,0]},{"opponent":"Doublade","move":{"category":"special move","defenderName":"Doublade","defenderHp":134,"movePct":0.97,"name":"Water Spout","totalDmg":130},"evs":[0,0,0,0,0,0]},{"opponent":"Spritzee","move":{"category":"special move","defenderName":"Spritzee","defenderHp":153,"movePct":0.69,"name":"Water Spout","totalDmg":106},"evs":[0,0,0,0,0,0]},{"opponent":"Aromatisse","move":{"category":"physical move","defenderName":"Aromatisse","defenderHp":176,"movePct":0.49,"name":"Iron Tail","totalDmg":87,"evs":[235,19,28,37,185,6]},"evs":[235,19,28,37,185,6]},{"opponent":"Swirlix","move":{"category":"special move","defenderName":"Swirlix","defenderHp":137,"movePct":0.89,"name":"Water Spout","totalDmg":122},"evs":[235,19,28,37,185,6]},{"opponent":"Slurpuff","move":{"category":"special move","defenderName":"Slurpuff","defenderHp":157,"movePct":0.63,"name":"Water Spout","totalDmg":99},"evs":[235,19,28,37,185,6]},{"opponent":"Inkay","move":{"category":"special move","defenderName":"Inkay","defenderHp":128,"movePct":1.11,"name":"Water Spout","totalDmg":142},"evs":[235,19,28,37,185,6]},{"opponent":"Malamar","move":{"category":"special move","defenderName":"Malamar","defenderHp":161,"movePct":0.61,"name":"Water Spout","totalDmg":99},"evs":[235,19,28,37,185,6]},{"opponent":"Binacle","move":{"category":"special move","defenderName":"Binacle","defenderHp":117,"movePct":1.14,"name":"Focus Blast","totalDmg":133},"evs":[235,19,28,37,185,6]},{"opponent":"Barbaracle","move":{"category":"special move","defenderName":"Barbaracle","defenderHp":147,"movePct":0.65,"name":"Focus Blast","totalDmg":96},"evs":[235,19,28,37,185,6]},{"opponent":"Helioptile","move":{"category":"special move","defenderName":"Helioptile","defenderHp":119,"movePct":1.34,"name":"Focus Blast","totalDmg":160},"evs":[235,19,28,37,185,6]},{"opponent":"Sylveon","move":{"category":"physical move","defenderName":"Sylveon","defenderHp":170,"movePct":0.55,"name":"Iron Tail","totalDmg":94},"evs":[0,0,0,0,0,0]},{"opponent":"Hawlucha","move":{"category":"special move","defenderName":"Hawlucha","defenderHp":153,"movePct":0.71,"name":"Water Spout","totalDmg":109,"evs":[196,35,46,72,5,156]},"evs":[196,35,46,72,5,156]},{"opponent":"Goomy","move":{"category":"physical move","defenderName":"Goomy","defenderHp":120,"movePct":1.48,"name":"Outrage","totalDmg":178},"evs":[196,35,46,72,5,156]},{"opponent":"Sliggoo","move":{"category":"physical move","defenderName":"Sliggoo","defenderHp":143,"movePct":0.94,"name":"Outrage","totalDmg":134},"evs":[196,35,46,72,5,156]},{"opponent":"Bergmite","move":{"category":"special move","defenderName":"Bergmite","defenderHp":130,"movePct":1.34,"name":"Focus Blast","totalDmg":174},"evs":[0,0,0,0,0,0]},{"opponent":"Avalugg","move":{"category":"special move","defenderName":"Avalugg","defenderHp":170,"movePct":0.86,"name":"Focus Blast","totalDmg":146},"evs":[0,0,0,0,0,0]},{"opponent":"Noibat","move":{"category":"special move","defenderName":"Noibat","defenderHp":115,"movePct":2.56,"name":"Blizzard","totalDmg":294},"evs":[0,0,0,0,0,0]},{"opponent":"Noivern","move":{"category":"special move","defenderName":"Noivern","defenderHp":160,"movePct":1.12,"name":"Blizzard","totalDmg":179},"evs":[0,0,0,0,0,0]},{"opponent":"Rowlet","move":{"category":"special move","defenderName":"Rowlet","defenderHp":143,"movePct":1.77,"name":"Blizzard","totalDmg":253,"evs":[57,5,20,244,8,176]},"evs":[57,5,20,244,8,176]},{"opponent":"Dartrix","move":{"category":"special move","defenderName":"Dartrix","defenderHp":153,"movePct":1.67,"name":"Blizzard","totalDmg":255},"evs":[0,0,0,0,0,0]},{"opponent":"Litten","move":{"category":"special move","defenderName":"Litten","defenderHp":120,"movePct":2.49,"name":"Water Spout","totalDmg":299},"evs":[0,0,0,0,0,0]},{"opponent":"Torracat","move":{"category":"special move","defenderName":"Torracat","defenderHp":140,"movePct":1.84,"name":"Water Spout","totalDmg":257,"evs":[198,63,44,78,14,113]},"evs":[198,63,44,78,14,113]},{"opponent":"Incineroar","move":{"category":"special move","defenderName":"Incineroar","defenderHp":170,"movePct":1.06,"name":"Water Spout","totalDmg":181},"evs":[198,63,44,78,14,113]},{"opponent":"Popplio","move":{"category":"physical move","defenderName":"Popplio","defenderHp":125,"movePct":0.55,"name":"Mega Kick","totalDmg":69},"evs":[198,63,44,78,14,113]},{"opponent":"Grubbin","move":{"category":"special move","defenderName":"Grubbin","defenderHp":122,"movePct":1.13,"name":"Water Spout","totalDmg":138},"evs":[0,0,0,0,0,0]},{"opponent":"Charjabug","move":{"category":"special move","defenderName":"Charjabug","defenderHp":132,"movePct":0.72,"name":"Water Spout","totalDmg":95},"evs":[0,0,0,0,0,0]},{"opponent":"Cutiefly","move":{"category":"special move","defenderName":"Cutiefly","defenderHp":115,"movePct":1.3,"name":"Water Spout","totalDmg":149,"evs":[78,66,21,154,23,168]},"evs":[78,66,21,154,23,168]},{"opponent":"Ribombee","move":{"category":"special move","defenderName":"Ribombee","defenderHp":135,"movePct":0.87,"name":"Water Spout","totalDmg":118},"evs":[0,0,0,0,0,0]},{"opponent":"Wishiwashi","move":{"category":"physical move","defenderName":"Wishiwashi","defenderHp":120,"movePct":0.97,"name":"Mega Kick","totalDmg":117},"evs":[0,0,0,0,0,0]},{"opponent":"Mareanie","move":{"category":"physical move","defenderName":"Mareanie","defenderHp":125,"movePct":0.78,"name":"Earthquake","totalDmg":97},"evs":[0,0,0,0,0,0]},{"opponent":"Mudbray","move":{"category":"special move","defenderName":"Mudbray","defenderHp":145,"movePct":1.66,"name":"Water Spout","totalDmg":240},"evs":[0,0,0,0,0,0]},{"opponent":"Dewpider","move":{"category":"physical move","defenderName":"Dewpider","defenderHp":113,"movePct":0.73,"name":"Rock Slide","totalDmg":83},"evs":[0,0,0,0,0,0]},{"opponent":"Salandit","move":{"category":"special move","defenderName":"Salandit","defenderHp":123,"movePct":2.43,"name":"Water Spout","totalDmg":299},"evs":[0,0,0,0,0,0]},{"opponent":"Stufful","move":{"category":"special move","defenderName":"Stufful","defenderHp":145,"movePct":0.95,"name":"Focus Blast","totalDmg":138},"evs":[0,0,0,0,0,0]},{"opponent":"Bounsweet","move":{"category":"special move","defenderName":"Bounsweet","defenderHp":117,"movePct":1.3,"name":"Blizzard","totalDmg":152},"evs":[0,0,0,0,0,0]},{"opponent":"Steenee","move":{"category":"special move","defenderName":"Steenee","defenderHp":127,"movePct":1.02,"name":"Blizzard","totalDmg":130},"evs":[0,0,0,0,0,0]},{"opponent":"Oranguru","move":{"category":"special move","defenderName":"Oranguru","defenderHp":165,"movePct":0.42,"name":"Water Spout","totalDmg":70,"evs":[103,47,173,40,92,55]},"evs":[103,47,173,40,92,55]},{"opponent":"Passimian","move":{"category":"special move","defenderName":"Passimian","defenderHp":175,"movePct":0.67,"name":"Water Spout","totalDmg":118},"evs":[103,47,173,40,92,55]},{"opponent":"Wimpod","move":{"category":"physical move","defenderName":"Wimpod","defenderHp":100,"movePct":1.05,"name":"Rock Slide","totalDmg":105},"evs":[103,47,173,40,92,55]},{"opponent":"Type: Null","move":{"category":"special move","defenderName":"Type: Null","defenderHp":170,"movePct":0.5,"name":"Focus Blast","totalDmg":85},"evs":[0,0,0,0,0,0]},{"opponent":"Jangmo-o","move":{"category":"special move","defenderName":"Jangmo-o","defenderHp":120,"movePct":1.13,"name":"Blizzard","totalDmg":136},"evs":[0,0,0,0,0,0]},{"opponent":"Hakamo-o","move":{"category":"special move","defenderName":"Hakamo-o","defenderHp":130,"movePct":0.76,"name":"Blizzard","totalDmg":99,"evs":[160,25,236,72,11,6]},"evs":[160,25,236,72,11,6]},{"opponent":"Meltan","move":{"category":"special move","defenderName":"Meltan","defenderHp":121,"movePct":1.44,"name":"Focus Blast","totalDmg":174},"evs":[0,0,0,0,0,0]},{"opponent":"Melmetal","move":{"category":"special move","defenderName":"Melmetal","defenderHp":210,"movePct":0.54,"name":"Focus Blast","totalDmg":114,"evs":[52,16,181,84,61,116]},"evs":[52,16,181,84,61,116]},{"opponent":"Grookey","move":{"category":"special move","defenderName":"Grookey","defenderHp":125,"movePct":1.3,"name":"Blizzard","totalDmg":162},"evs":[0,0,0,0,0,0]},{"opponent":"Scorbunny","move":{"category":"special move","defenderName":"Scorbunny","defenderHp":125,"movePct":2.39,"name":"Water Spout","totalDmg":299},"evs":[0,0,0,0,0,0]},{"opponent":"Raboot","move":{"category":"special move","defenderName":"Raboot","defenderHp":140,"movePct":1.61,"name":"Water Spout","totalDmg":225,"evs":[126,128,23,5,16,212]},"evs":[126,128,23,5,16,212]},{"opponent":"Cinderace","move":{"category":"special move","defenderName":"Cinderace","defenderHp":155,"movePct":1.24,"name":"Water Spout","totalDmg":192},"evs":[0,0,0,0,0,0]},{"opponent":"Sobble","move":{"category":"special move","defenderName":"Sobble","defenderHp":125,"movePct":0.64,"name":"Focus Blast","totalDmg":80},"evs":[0,0,0,0,0,0]},{"opponent":"Drizzile","move":{"category":"special move","defenderName":"Drizzile","defenderHp":140,"movePct":0.46,"name":"Focus Blast","totalDmg":64,"evs":[144,29,57,202,48,30]},"evs":[144,29,57,202,48,30]},{"opponent":"Skwovet","move":{"category":"special move","defenderName":"Skwovet","defenderHp":145,"movePct":1.2,"name":"Focus Blast","totalDmg":174},"evs":[0,0,0,0,0,0]},{"opponent":"Greedent","move":{"category":"special move","defenderName":"Greedent","defenderHp":195,"movePct":0.52,"name":"Focus Blast","totalDmg":102,"evs":[29,28,248,7,107,91]},"evs":[29,28,248,7,107,91]},{"opponent":"Rookidee","move":{"category":"special move","defenderName":"Rookidee","defenderHp":113,"movePct":1.45,"name":"Water Spout","totalDmg":164},"evs":[29,28,248,7,107,91]},{"opponent":"Corvisquire","move":{"category":"special move","defenderName":"Corvisquire","defenderHp":143,"movePct":0.85,"name":"Water Spout","totalDmg":121},"evs":[29,28,248,7,107,91]},{"opponent":"Corviknight","move":{"category":"special move","defenderName":"Corviknight","defenderHp":173,"movePct":0.5,"name":"Water Spout","totalDmg":87},"evs":[29,28,248,7,107,91]},{"opponent":"Blipbug","move":{"category":"physical move","defenderName":"Blipbug","defenderHp":100,"movePct":1.53,"name":"Rock Slide","totalDmg":153},"evs":[29,28,248,7,107,91]},{"opponent":"Dottler","move":{"category":"special move","defenderName":"Dottler","defenderHp":125,"movePct":0.66,"name":"Water Spout","totalDmg":83},"evs":[29,28,248,7,107,91]},{"opponent":"Orbeetle","move":{"category":"special move","defenderName":"Orbeetle","defenderHp":135,"movePct":0.49,"name":"Water Spout","totalDmg":66,"evs":[59,90,64,95,51,151]},"evs":[59,90,64,95,51,151]},{"opponent":"Nickit","move":{"category":"special move","defenderName":"Nickit","defenderHp":115,"movePct":1.3,"name":"Focus Blast","totalDmg":149},"evs":[59,90,64,95,51,151]},{"opponent":"Thievul","move":{"category":"special move","defenderName":"Thievul","defenderHp":145,"movePct":0.67,"name":"Focus Blast","totalDmg":97},"evs":[59,90,64,95,51,151]},{"opponent":"Gossifleur","move":{"category":"special move","defenderName":"Gossifleur","defenderHp":115,"movePct":1.07,"name":"Blizzard","totalDmg":123},"evs":[0,0,0,0,0,0]},{"opponent":"Wooloo","move":{"category":"special move","defenderName":"Wooloo","defenderHp":117,"movePct":1.26,"name":"Focus Blast","totalDmg":148},"evs":[0,0,0,0,0,0]},{"opponent":"Dubwool","move":{"category":"special move","defenderName":"Dubwool","defenderHp":147,"movePct":0.61,"name":"Focus Blast","totalDmg":89,"evs":[44,67,91,171,64,73]},"evs":[44,67,91,171,64,73]},{"opponent":"Chewtle","move":{"category":"special move","defenderName":"Chewtle","defenderHp":125,"movePct":0.79,"name":"Focus Blast","totalDmg":99},"evs":[44,67,91,171,64,73]},{"opponent":"Rolycoly","move":{"category":"special move","defenderName":"Rolycoly","defenderHp":105,"movePct":2.45,"name":"Water Spout","totalDmg":257},"evs":[0,0,0,0,0,0]},{"opponent":"Carkol","move":{"category":"special move","defenderName":"Carkol","defenderHp":155,"movePct":2.59,"name":"Water Spout","totalDmg":402},"evs":[0,0,0,0,0,0]},{"opponent":"Coalossal","move":{"category":"special move","defenderName":"Coalossal","defenderHp":185,"movePct":1.79,"name":"Water Spout","totalDmg":331},"evs":[0,0,0,0,0,0]},{"opponent":"Applin","move":{"category":"special move","defenderName":"Applin","defenderHp":115,"movePct":2.56,"name":"Blizzard","totalDmg":294},"evs":[0,0,0,0,0,0]},{"opponent":"Flapple","move":{"category":"special move","defenderName":"Flapple","defenderHp":145,"movePct":1.53,"name":"Blizzard","totalDmg":222},"evs":[0,0,0,0,0,0]},{"opponent":"Silicobra","move":{"category":"special move","defenderName":"Silicobra","defenderHp":127,"movePct":2.02,"name":"Water Spout","totalDmg":257},"evs":[0,0,0,0,0,0]},{"opponent":"Sandaconda","move":{"category":"special move","defenderName":"Sandaconda","defenderHp":147,"movePct":1.37,"name":"Water Spout","totalDmg":201},"evs":[0,0,0,0,0,0]},{"opponent":"Cramorant","move":{"category":"physical move","defenderName":"Cramorant","defenderHp":145,"movePct":0.55,"name":"Rock Slide","totalDmg":80},"evs":[0,0,0,0,0,0]},{"opponent":"Arrokuda","move":{"category":"special move","defenderName":"Arrokuda","defenderHp":116,"movePct":0.82,"name":"Focus Blast","totalDmg":95},"evs":[0,0,0,0,0,0]},{"opponent":"Barraskewda","move":{"category":"special move","defenderName":"Barraskewda","defenderHp":136,"movePct":0.51,"name":"Focus Blast","totalDmg":69},"evs":[0,0,0,0,0,0]},{"opponent":"Toxel","move":{"category":"physical move","defenderName":"Toxel","defenderHp":115,"movePct":2.49,"name":"Earthquake","totalDmg":286},"evs":[0,0,0,0,0,0]},{"opponent":"Toxtricity","move":{"category":"physical move","defenderName":"Toxtricity","defenderHp":150,"movePct":1.19,"name":"Earthquake","totalDmg":178},"evs":[0,0,0,0,0,0]},{"opponent":"Sizzlipede","move":{"category":"special move","defenderName":"Sizzlipede","defenderHp":125,"movePct":2.06,"name":"Water Spout","totalDmg":257,"evs":[1,184,177,79,10,59]},"evs":[1,184,177,79,10,59]},{"opponent":"Centiskorch","move":{"category":"special move","defenderName":"Centiskorch","defenderHp":175,"movePct":1.03,"name":"Water Spout","totalDmg":181},"evs":[0,0,0,0,0,0]},{"opponent":"Clobbopus","move":{"category":"special move","defenderName":"Clobbopus","defenderHp":125,"movePct":1.02,"name":"Water Spout","totalDmg":128},"evs":[0,0,0,0,0,0]},{"opponent":"Sinistea","move":{"category":"special move","defenderName":"Sinistea","defenderHp":115,"movePct":1.05,"name":"Water Spout","totalDmg":121},"evs":[0,0,0,0,0,0]},{"opponent":"Hatenna","move":{"category":"special move","defenderName":"Hatenna","defenderHp":117,"movePct":1.05,"name":"Water Spout","totalDmg":123},"evs":[0,0,0,0,0,0]},{"opponent":"Hattrem","move":{"category":"special move","defenderName":"Hattrem","defenderHp":132,"movePct":0.73,"name":"Water Spout","totalDmg":97},"evs":[0,0,0,0,0,0]},{"opponent":"Impidimp","move":{"category":"physical move","defenderName":"Impidimp","defenderHp":120,"movePct":1.31,"name":"Iron Tail","totalDmg":157},"evs":[0,0,0,0,0,0]},{"opponent":"Morgrem","move":{"category":"special move","defenderName":"Morgrem","defenderHp":140,"movePct":0.86,"name":"Water Spout","totalDmg":120},"evs":[0,0,0,0,0,0]},{"opponent":"Obstagoon","move":{"category":"special move","defenderName":"Obstagoon","defenderHp":168,"movePct":1.15,"name":"Focus Blast","totalDmg":193},"evs":[0,0,0,0,0,0]},{"opponent":"Cursola","move":{"category":"physical move","defenderName":"Cursola","defenderHp":135,"movePct":0.67,"name":"Crunch","totalDmg":91,"evs":[121,8,25,54,141,161]},"evs":[121,8,25,54,141,161]},{"opponent":"Runerigus","move":{"category":"special move","defenderName":"Runerigus","defenderHp":133,"movePct":1.1,"name":"Water Spout","totalDmg":146},"evs":[0,0,0,0,0,0]},{"opponent":"Milcery","move":{"category":"physical move","defenderName":"Milcery","defenderHp":120,"movePct":1.09,"name":"Iron Tail","totalDmg":131},"evs":[0,0,0,0,0,0]},{"opponent":"Falinks","move":{"category":"special move","defenderName":"Falinks","defenderHp":140,"movePct":0.8,"name":"Water Spout","totalDmg":112,"evs":[60,23,140,83,171,33]},"evs":[60,23,140,83,171,33]},{"opponent":"Snom","move":{"category":"physical move","defenderName":"Snom","defenderHp":105,"movePct":2.06,"name":"Rock Slide","totalDmg":216},"evs":[0,0,0,0,0,0]},{"opponent":"Frosmoth","move":{"category":"physical move","defenderName":"Frosmoth","defenderHp":145,"movePct":1.04,"name":"Rock Slide","totalDmg":151,"evs":[123,147,29,102,76,33]},"evs":[123,147,29,102,76,33]},{"opponent":"Stonjourner","move":{"category":"special move","defenderName":"Stonjourner","defenderHp":175,"movePct":2.86,"name":"Water Spout","totalDmg":501},"evs":[123,147,29,102,76,33]},{"opponent":"Indeedee","move":{"category":"physical move","defenderName":"Indeedee","defenderHp":135,"movePct":0.63,"name":"Crunch","totalDmg":85,"evs":[33,1,129,50,110,187]},"evs":[33,1,129,50,110,187]},{"opponent":"Dracovish","move":{"category":"physical move","defenderName":"Dracovish","defenderHp":165,"movePct":0.48,"name":"Outrage","totalDmg":80,"evs":[2,167,38,94,61,148]},"evs":[2,167,38,94,61,148]},{"opponent":"Arctovish","move":{"category":"special move","defenderName":"Arctovish","defenderHp":165,"movePct":0.59,"name":"Focus Blast","totalDmg":98},"evs":[2,167,38,94,61,148]},{"opponent":"Duraludon","move":{"category":"special move","defenderName":"Duraludon","defenderHp":145,"movePct":1.06,"name":"Focus Blast","totalDmg":153},"evs":[0,0,0,0,0,0]},{"opponent":"Dreepy","move":{"category":"physical move","defenderName":"Dreepy","defenderHp":103,"movePct":1.83,"name":"Outrage","totalDmg":188},"evs":[0,0,0,0,0,0]},{"opponent":"Drakloak","move":{"category":"physical move","defenderName":"Drakloak","defenderHp":143,"movePct":0.94,"name":"Outrage","totalDmg":135},"evs":[0,0,0,0,0,0]}],"losses":[{"opponent":"Venusaur","move":{"category":"special move","defenderName":"Blastoise","defenderHp":154,"movePct":1.1,"name":"Leaf Storm","totalDmg":170},"evs":[0,0,0,0,0,0]},{"opponent":"Blastoise","move":{"category":"physical move","defenderName":"Blastoise","defenderHp":154,"movePct":0.31,"name":"Mega Kick","totalDmg":47},"evs":[0,0,0,0,0,0]},{"opponent":"Bulbasaur","move":{"category":"special move","defenderName":"Blastoise","defenderHp":164,"movePct":0.66,"name":"Leaf Storm","totalDmg":109},"evs":[0,0,0,0,0,0]},{"opponent":"Ivysaur","move":{"category":"special move","defenderName":"Blastoise","defenderHp":154,"movePct":0.93,"name":"Leaf Storm","totalDmg":143},"evs":[0,0,0,0,0,0]},{"opponent":"Wartortle","move":{"category":"physical move","defenderName":"Blastoise","defenderHp":169,"movePct":0.21,"name":"Mega Kick","totalDmg":35},"evs":[0,0,0,0,0,0]},{"opponent":"Pikachu","move":{"category":"physical move","defenderName":"Blastoise","defenderHp":154,"movePct":0.68,"name":"Volt Tackle","totalDmg":105},"evs":[0,0,0,0,0,0]},{"opponent":"Raichu","move":{"category":"physical move","defenderName":"Blastoise","defenderHp":154,"movePct":0.98,"name":"Volt Tackle","totalDmg":151},"evs":[0,0,0,0,0,0]},{"opponent":"Clefable","move":{"category":"special move","defenderName":"Blastoise","defenderHp":154,"movePct":0.6,"name":"Thunder","totalDmg":93},"evs":[0,0,0,0,0,0]},{"opponent":"Oddish","move":{"category":"special move","defenderName":"Blastoise","defenderHp":154,"movePct":0.82,"name":"Petal Dance","totalDmg":126},"evs":[0,0,0,0,0,0]},{"opponent":"Gloom","move":{"category":"special move","defenderName":"Blastoise","defenderHp":154,"movePct":0.9,"name":"Petal Dance","totalDmg":139},"evs":[0,0,0,0,0,0]},{"opponent":"Vileplume","move":{"category":"special move","defenderName":"Blastoise","defenderHp":154,"movePct":1.1,"name":"Petal Dance","totalDmg":170},"evs":[0,0,0,0,0,0]},{"opponent":"Machamp","move":{"category":"physical move","defenderName":"Blastoise","defenderHp":164,"movePct":0.55,"name":"Superpower","totalDmg":91},"evs":[0,0,0,0,0,0]},{"opponent":"Haunter","move":{"category":"special move","defenderName":"Blastoise","defenderHp":161,"movePct":0.55,"name":"Thunderbolt","totalDmg":88},"evs":[0,0,0,0,0,0]},{"opponent":"Gengar","move":{"category":"special move","defenderName":"Blastoise","defenderHp":154,"movePct":0.78,"name":"Thunder","totalDmg":120},"evs":[0,0,0,0,0,0]},{"opponent":"Hitmonlee","move":{"category":"physical move","defenderName":"Blastoise","defenderHp":154,"movePct":0.67,"name":"High Jump Kick","totalDmg":103},"evs":[0,0,0,0,0,0]},{"opponent":"Hitmonchan","move":{"category":"physical move","defenderName":"Blastoise","defenderHp":154,"movePct":0.69,"name":"Focus Punch","totalDmg":106},"evs":[0,0,0,0,0,0]},{"opponent":"Weezing","move":{"category":"physical move","defenderName":"Blastoise","defenderHp":154,"movePct":0.66,"name":"Explosion","totalDmg":102},"evs":[0,0,0,0,0,0]},{"opponent":"Seaking","move":{"category":"physical move","defenderName":"Blastoise","defenderHp":159,"movePct":0.27,"name":"Megahorn","totalDmg":43},"evs":[0,0,0,0,0,0]},{"opponent":"Mr. Mime","move":{"category":"special move","defenderName":"Blastoise","defenderHp":154,"movePct":0.62,"name":"Thunder","totalDmg":96},"evs":[0,0,0,0,0,0]},{"opponent":"Gyarados","move":{"category":"physical move","defenderName":"Blastoise","defenderHp":159,"movePct":0.76,"name":"Power Whip","totalDmg":121},"evs":[0,0,0,0,0,0]},{"opponent":"Lapras","move":{"category":"special move","defenderName":"Blastoise","defenderHp":154,"movePct":0.16,"name":"Ancient Power","totalDmg":24},"evs":[0,0,0,0,0,0]},{"opponent":"Vaporeon","move":{"category":"physical move","defenderName":"Blastoise","defenderHp":154,"movePct":0.07,"name":"Double Kick","totalDmg":11},"evs":[0,0,0,0,0,0]},{"opponent":"Snorlax","move":{"category":"physical move","defenderName":"Blastoise","defenderHp":154,"movePct":null,"name":"Double-Edge","totalDmg":null},"evs":[0,0,0,0,0,0]},{"opponent":"Mewtwo","move":{"category":"special move","defenderName":"Blastoise","defenderHp":154,"movePct":0.9,"name":"Thunder","totalDmg":138},"evs":[0,0,0,0,0,0]},{"opponent":"Mew","move":{"category":"physical move","defenderName":"Blastoise","defenderHp":154,"movePct":0.45,"name":"Thunder Punch","totalDmg":70},"evs":[0,0,0,0,0,0]},{"opponent":"Lanturn","move":{"category":"special move","defenderName":"Blastoise","defenderHp":169,"movePct":0.6,"name":"Thunder","totalDmg":102},"evs":[0,0,0,0,0,0]},{"opponent":"Bellossom","move":{"category":"special move","defenderName":"Blastoise","defenderHp":154,"movePct":1.02,"name":"Leaf Storm","totalDmg":157},"evs":[0,0,0,0,0,0]},{"opponent":"Umbreon","move":{"category":"physical move","defenderName":"Blastoise","defenderHp":154,"movePct":0.07,"name":"Double Kick","totalDmg":11},"evs":[0,0,0,0,0,0]},{"opponent":"Octillery","move":{"category":"special move","defenderName":"Blastoise","defenderHp":154,"movePct":0.54,"name":"Energy Ball","totalDmg":83},"evs":[50,110,220,50,74,6]},{"opponent":"Mantine","move":{"category":"special move","defenderName":"Blastoise","defenderHp":160,"movePct":0.36,"name":"Hurricane","totalDmg":57},"evs":[0,0,0,0,0,0]},{"opponent":"Celebi","move":{"category":"special move","defenderName":"Blastoise","defenderHp":154,"movePct":1.1,"name":"Leaf Storm","totalDmg":170},"evs":[0,0,0,0,0,0]},{"opponent":"Ludicolo","move":{"category":"special move","defenderName":"Blastoise","defenderHp":157,"movePct":0.82,"name":"Leaf Storm","totalDmg":129},"evs":[0,0,0,0,0,0]},{"opponent":"Shiftry","move":{"category":"special move","defenderName":"Blastoise","defenderHp":154,"movePct":1.02,"name":"Leaf Storm","totalDmg":157},"evs":[0,0,0,0,0,0]},{"opponent":"Pelipper","move":{"category":"special move","defenderName":"Blastoise","defenderHp":154,"movePct":0.45,"name":"Hurricane","totalDmg":69},"evs":[0,0,0,0,0,0]},{"opponent":"Manectric","move":{"category":"special move","defenderName":"Blastoise","defenderHp":154,"movePct":0.98,"name":"Thunder","totalDmg":151},"evs":[0,0,0,0,0,0]},{"opponent":"Roselia","move":{"category":"special move","defenderName":"Blastoise","defenderHp":154,"movePct":1.1,"name":"Leaf Storm","totalDmg":170},"evs":[0,0,0,0,0,0]},{"opponent":"Wailmer","move":{"category":"physical move","defenderName":"Blastoise","defenderHp":154,"movePct":null,"name":"Double-Edge","totalDmg":null},"evs":[0,0,0,0,0,0]},{"opponent":"Wailord","move":{"category":"physical move","defenderName":"Blastoise","defenderHp":154,"movePct":null,"name":"Double-Edge","totalDmg":null},"evs":[0,0,0,0,0,0]},{"opponent":"Claydol","move":{"category":"special move","defenderName":"Blastoise","defenderHp":154,"movePct":null,"name":"Mud-Slap","totalDmg":null},"evs":[0,0,0,0,0,0]},{"opponent":"Milotic","move":{"category":"special move","defenderName":"Blastoise","defenderHp":162,"movePct":0.2,"name":"Hydro Pump","totalDmg":32},"evs":[0,0,0,0,0,0]},{"opponent":"Jirachi","move":{"category":"special move","defenderName":"Blastoise","defenderHp":182,"movePct":0.52,"name":"Thunder","totalDmg":94},"evs":[0,0,0,0,0,0]},{"opponent":"Roserade","move":{"category":"special move","defenderName":"Blastoise","defenderHp":154,"movePct":1.33,"name":"Leaf Storm","totalDmg":205},"evs":[0,0,0,0,0,0]},{"opponent":"Cherrim","move":{"category":"special move","defenderName":"Blastoise","defenderHp":164,"movePct":0.74,"name":"Petal Dance","totalDmg":121},"evs":[0,0,0,0,0,0]},{"opponent":"Gastrodon","move":{"category":"special move","defenderName":"Blastoise","defenderHp":179,"movePct":0.31,"name":"Earth Power","totalDmg":55},"evs":[0,0,0,0,0,0]},{"opponent":"Drifblim","move":{"category":"physical move","defenderName":"Blastoise","defenderHp":154,"movePct":0.6,"name":"Explosion","totalDmg":93},"evs":[0,0,0,0,0,0]},{"opponent":"Munchlax","move":{"category":"physical move","defenderName":"Blastoise","defenderHp":174,"movePct":null,"name":"Double-Edge","totalDmg":null},"evs":[0,0,0,0,0,0]},{"opponent":"Lucario","move":{"category":"physical move","defenderName":"Blastoise","defenderHp":154,"movePct":0.62,"name":"High Jump Kick","totalDmg":95},"evs":[0,0,0,0,0,0]},{"opponent":"Abomasnow","move":{"category":"physical move","defenderName":"Blastoise","defenderHp":154,"movePct":null,"name":"Double-Edge","totalDmg":null},"evs":[0,0,0,0,0,0]},{"opponent":"Gallade","move":{"category":"physical move","defenderName":"Blastoise","defenderHp":155,"movePct":0.63,"name":"Close Combat","totalDmg":97},"evs":[0,0,0,0,0,0]},{"opponent":"Dusknoir","move":{"category":"physical move","defenderName":"Blastoise","defenderHp":154,"movePct":0.45,"name":"Thunder Punch","totalDmg":70},"evs":[0,0,0,0,0,0]},{"opponent":"Rotom","move":{"category":"special move","defenderName":"Blastoise","defenderHp":170,"movePct":0.52,"name":"Thunder","totalDmg":88},"evs":[0,0,0,0,0,0]},{"opponent":"Musharna","move":{"category":"special move","defenderName":"Blastoise","defenderHp":154,"movePct":0.55,"name":"Energy Ball","totalDmg":84},"evs":[74,61,27,77,219,52]},{"opponent":"Unfezant","move":{"category":"physical move","defenderName":"Blastoise","defenderHp":163,"movePct":0.55,"name":"Brave Bird","totalDmg":89},"evs":[0,0,0,0,0,0]},{"opponent":"Throh","move":{"category":"physical move","defenderName":"Blastoise","defenderHp":174,"movePct":0.45,"name":"Superpower","totalDmg":79},"evs":[0,0,0,0,0,0]},{"opponent":"Sawk","move":{"category":"physical move","defenderName":"Blastoise","defenderHp":154,"movePct":0.64,"name":"Close Combat","totalDmg":98},"evs":[0,0,0,0,0,0]},{"opponent":"Whimsicott","move":{"category":"special move","defenderName":"Blastoise","defenderHp":154,"movePct":0.64,"name":"Energy Ball","totalDmg":98},"evs":[0,0,0,0,0,0]},{"opponent":"Maractus","move":{"category":"special move","defenderName":"Blastoise","defenderHp":168,"movePct":0.99,"name":"Leaf Storm","totalDmg":166},"evs":[0,0,0,0,0,0]},{"opponent":"Sigilyph","move":{"category":"special move","defenderName":"Blastoise","defenderHp":154,"movePct":0.53,"name":"Energy Ball","totalDmg":81},"evs":[0,0,0,0,0,0]},{"opponent":"Garbodor","move":{"category":"physical move","defenderName":"Blastoise","defenderHp":154,"movePct":0.69,"name":"Explosion","totalDmg":107},"evs":[0,0,0,0,0,0]},{"opponent":"Duosion","move":{"category":"special move","defenderName":"Blastoise","defenderHp":154,"movePct":0.75,"name":"Thunder","totalDmg":116},"evs":[0,0,0,0,0,0]},{"opponent":"Reuniclus","move":{"category":"special move","defenderName":"Blastoise","defenderHp":154,"movePct":0.75,"name":"Thunder","totalDmg":116},"evs":[0,0,0,0,0,0]},{"opponent":"Vanilluxe","move":{"category":"physical move","defenderName":"Blastoise","defenderHp":169,"movePct":0.62,"name":"Explosion","totalDmg":104},"evs":[0,0,0,0,0,0]},{"opponent":"Escavalier","move":{"category":"physical move","defenderName":"Blastoise","defenderHp":154,"movePct":0.68,"name":"Megahorn","totalDmg":105},"evs":[0,0,0,0,0,0]},{"opponent":"Jellicent","move":{"category":"special move","defenderName":"Blastoise","defenderHp":154,"movePct":0.45,"name":"Energy Ball","totalDmg":70},"evs":[0,0,0,0,0,0]},{"opponent":"Galvantula","move":{"category":"special move","defenderName":"Blastoise","defenderHp":160,"movePct":0.88,"name":"Thunder","totalDmg":140},"evs":[0,0,0,0,0,0]},{"opponent":"Ferrothorn","move":{"category":"physical move","defenderName":"Blastoise","defenderHp":154,"movePct":1.01,"name":"Power Whip","totalDmg":156},"evs":[0,0,0,0,0,0]},{"opponent":"Beheeyem","move":{"category":"special move","defenderName":"Blastoise","defenderHp":154,"movePct":0.62,"name":"Thunderbolt","totalDmg":95},"evs":[0,0,0,0,0,0]},{"opponent":"Haxorus","move":{"category":"physical move","defenderName":"Blastoise","defenderHp":180,"movePct":0.59,"name":"Outrage","totalDmg":106},"evs":[0,0,0,0,0,0]},{"opponent":"Shelmet","move":{"category":"physical move","defenderName":"Blastoise","defenderHp":163,"movePct":null,"name":"Double-Edge","totalDmg":null},"evs":[0,0,0,0,0,0]},{"opponent":"Accelgor","move":{"category":"physical move","defenderName":"Blastoise","defenderHp":154,"movePct":null,"name":"Double-Edge","totalDmg":null},"evs":[0,0,0,0,0,0]},{"opponent":"Stunfisk","move":{"category":"special move","defenderName":"Blastoise","defenderHp":154,"movePct":0.8,"name":"Thunder","totalDmg":123},"evs":[0,0,0,0,0,0]},{"opponent":"Braviary","move":{"category":"physical move","defenderName":"Blastoise","defenderHp":164,"movePct":0.55,"name":"Thrash","totalDmg":90},"evs":[0,0,0,0,0,0]},{"opponent":"Mandibuzz","move":{"category":"physical move","defenderName":"Blastoise","defenderHp":154,"movePct":0.38,"name":"Brave Bird","totalDmg":59},"evs":[0,0,0,0,0,0]},{"opponent":"Terrakion","move":{"category":"physical move","defenderName":"Blastoise","defenderHp":154,"movePct":0.66,"name":"Close Combat","totalDmg":101},"evs":[0,0,0,0,0,0]},{"opponent":"Virizion","move":{"category":"special move","defenderName":"Blastoise","defenderHp":154,"movePct":1.02,"name":"Leaf Storm","totalDmg":157},"evs":[0,0,0,0,0,0]},{"opponent":"Reshiram","move":{"category":"physical move","defenderName":"Blastoise","defenderHp":154,"movePct":0.62,"name":"Outrage","totalDmg":95},"evs":[0,0,0,0,0,0]},{"opponent":"Zekrom","move":{"category":"physical move","defenderName":"Blastoise","defenderHp":154,"movePct":1.62,"name":"Bolt Strike","totalDmg":249},"evs":[0,0,0,0,0,0]},{"opponent":"Keldeo","move":{"category":"special move","defenderName":"Blastoise","defenderHp":164,"movePct":0.53,"name":"Focus Blast","totalDmg":87},"evs":[0,0,0,0,0,0]},{"opponent":"Pangoro","move":{"category":"physical move","defenderName":"Blastoise","defenderHp":175,"movePct":0.54,"name":"Superpower","totalDmg":94},"evs":[0,0,0,0,0,0]},{"opponent":"Aegislash","move":{"category":"physical move","defenderName":"Blastoise","defenderHp":154,"movePct":0.26,"name":"Head Smash","totalDmg":40},"evs":[0,0,0,0,0,0]},{"opponent":"Heliolisk","move":{"category":"special move","defenderName":"Blastoise","defenderHp":183,"movePct":0.72,"name":"Thunder","totalDmg":132},"evs":[0,0,0,0,0,0]},{"opponent":"Goodra","move":{"category":"physical move","defenderName":"Blastoise","defenderHp":179,"movePct":0.58,"name":"Power Whip","totalDmg":104},"evs":[0,0,0,0,0,0]},{"opponent":"Phantump","move":{"category":"physical move","defenderName":"Blastoise","defenderHp":154,"movePct":0.81,"name":"Wood Hammer","totalDmg":124},"evs":[0,0,0,0,0,0]},{"opponent":"Trevenant","move":{"category":"physical move","defenderName":"Blastoise","defenderHp":154,"movePct":1.15,"name":"Wood Hammer","totalDmg":177},"evs":[0,0,0,0,0,0]},{"opponent":"Pumpkaboo","move":{"category":"physical move","defenderName":"Blastoise","defenderHp":154,"movePct":0.53,"name":"Seed Bomb","totalDmg":81},"evs":[0,0,0,0,0,0]},{"opponent":"Gourgeist","move":{"category":"physical move","defenderName":"Blastoise","defenderHp":154,"movePct":0.98,"name":"Power Whip","totalDmg":151},"evs":[0,0,0,0,0,0]},{"opponent":"Decidueye","move":{"category":"special move","defenderName":"Blastoise","defenderHp":154,"movePct":1.1,"name":"Leaf Storm","totalDmg":170},"evs":[0,0,0,0,0,0]},{"opponent":"Brionne","move":{"category":"special move","defenderName":"Blastoise","defenderHp":179,"movePct":0.21,"name":"Moonblast","totalDmg":38},"evs":[0,0,0,0,0,0]},{"opponent":"Primarina","move":{"category":"special move","defenderName":"Blastoise","defenderHp":154,"movePct":0.62,"name":"Energy Ball","totalDmg":96},"evs":[0,0,0,0,0,0]},{"opponent":"Vikavolt","move":{"category":"special move","defenderName":"Blastoise","defenderHp":154,"movePct":1.05,"name":"Thunderbolt","totalDmg":162},"evs":[0,0,0,0,0,0]},{"opponent":"Toxapex","move":{"category":"physical move","defenderName":"Blastoise","defenderHp":154,"movePct":0.37,"name":"Gunk Shot","totalDmg":57},"evs":[0,0,0,0,0,0]},{"opponent":"Mudsdale","move":{"category":"physical move","defenderName":"Blastoise","defenderHp":154,"movePct":null,"name":"Double-Edge","totalDmg":null},"evs":[0,0,0,0,0,0]},{"opponent":"Araquanid","move":{"category":"physical move","defenderName":"Blastoise","defenderHp":154,"movePct":0.27,"name":"Lunge","totalDmg":42},"evs":[0,0,0,0,0,0]},{"opponent":"Morelull","move":{"category":"special move","defenderName":"Blastoise","defenderHp":154,"movePct":0.56,"name":"Energy Ball","totalDmg":86},"evs":[0,0,0,0,0,0]},{"opponent":"Shiinotic","move":{"category":"special move","defenderName":"Blastoise","defenderHp":154,"movePct":0.71,"name":"Energy Ball","totalDmg":110},"evs":[0,0,0,0,0,0]},{"opponent":"Salazzle","move":{"category":"special move","defenderName":"Blastoise","defenderHp":154,"movePct":0.56,"name":"Belch","totalDmg":86},"evs":[0,0,0,0,0,0]},{"opponent":"Bewear","move":{"category":"physical move","defenderName":"Blastoise","defenderHp":154,"movePct":0.64,"name":"Thrash","totalDmg":98},"evs":[0,0,0,0,0,0]},{"opponent":"Tsareena","move":{"category":"physical move","defenderName":"Blastoise","defenderHp":154,"movePct":1.23,"name":"Power Whip","totalDmg":190},"evs":[0,0,0,0,0,0]},{"opponent":"Golisopod","move":{"category":"physical move","defenderName":"Blastoise","defenderHp":167,"movePct":0.38,"name":"First Impression","totalDmg":63},"evs":[0,0,0,0,0,0]},{"opponent":"Silvally","move":{"category":"physical move","defenderName":"Blastoise","defenderHp":154,"movePct":null,"name":"Multi-Attack","totalDmg":null},"evs":[0,0,0,0,0,0]},{"opponent":"Turtonator","move":{"category":"physical move","defenderName":"Blastoise","defenderHp":154,"movePct":0.59,"name":"Explosion","totalDmg":91},"evs":[0,0,0,0,0,0]},{"opponent":"Togedemaru","move":{"category":"physical move","defenderName":"Blastoise","defenderHp":154,"movePct":0.79,"name":"Wild Charge","totalDmg":122},"evs":[0,0,0,0,0,0]},{"opponent":"Mimikyu","move":{"category":"physical move","defenderName":"Blastoise","defenderHp":154,"movePct":0.65,"name":"Wood Hammer","totalDmg":100},"evs":[0,0,0,0,0,0]},{"opponent":"Drampa","move":{"category":"special move","defenderName":"Blastoise","defenderHp":154,"movePct":0.81,"name":"Thunder","totalDmg":124},"evs":[0,0,0,0,0,0]},{"opponent":"Dhelmise","move":{"category":"physical move","defenderName":"Blastoise","defenderHp":154,"movePct":1.33,"name":"Power Whip","totalDmg":205},"evs":[0,0,0,0,0,0]},{"opponent":"Kommo-o","move":{"category":"physical move","defenderName":"Blastoise","defenderHp":174,"movePct":0.51,"name":"Focus Punch","totalDmg":88},"evs":[0,0,0,0,0,0]},{"opponent":"Solgaleo","move":{"category":"physical move","defenderName":"Blastoise","defenderHp":154,"movePct":0.69,"name":"Wild Charge","totalDmg":107},"evs":[0,0,0,0,0,0]},{"opponent":"Lunala","move":{"category":"special move","defenderName":"Blastoise","defenderHp":154,"movePct":0.81,"name":"Thunder","totalDmg":125},"evs":[0,0,0,0,0,0]},{"opponent":"Necrozma","move":{"category":"special move","defenderName":"Blastoise","defenderHp":154,"movePct":0.62,"name":"Future Sight","totalDmg":96},"evs":[0,0,0,0,0,0]},{"opponent":"Marshadow","move":{"category":"physical move","defenderName":"Blastoise","defenderHp":154,"movePct":0.64,"name":"Close Combat","totalDmg":98},"evs":[0,0,0,0,0,0]},{"opponent":"Zeraora","move":{"category":"physical move","defenderName":"Blastoise","defenderHp":154,"movePct":null,"name":"Power-Up Punch","totalDmg":null},"evs":[0,0,0,0,0,0]},{"opponent":"Thwackey","move":{"category":"physical move","defenderName":"Blastoise","defenderHp":154,"movePct":0.94,"name":"Wood Hammer","totalDmg":144},"evs":[0,0,0,0,0,0]},{"opponent":"Rillaboom","move":{"category":"physical move","defenderName":"Blastoise","defenderHp":154,"movePct":1.28,"name":"Wood Hammer","totalDmg":197},"evs":[0,0,0,0,0,0]},{"opponent":"Inteleon","move":{"category":"special move","defenderName":"Blastoise","defenderHp":172,"movePct":0.24,"name":"Hydro Pump","totalDmg":41},"evs":[0,0,0,0,0,0]},{"opponent":"Eldegoss","move":{"category":"special move","defenderName":"Blastoise","defenderHp":154,"movePct":0.93,"name":"Leaf Storm","totalDmg":143},"evs":[0,0,0,0,0,0]},{"opponent":"Drednaw","move":{"category":"physical move","defenderName":"Blastoise","defenderHp":160,"movePct":0.66,"name":"Head Smash","totalDmg":105},"evs":[0,0,0,0,0,0]},{"opponent":"Yamper","move":{"category":"physical move","defenderName":"Blastoise","defenderHp":154,"movePct":null,"name":"Double-Edge","totalDmg":null},"evs":[0,0,0,0,0,0]},{"opponent":"Boltund","move":{"category":"physical move","defenderName":"Blastoise","defenderHp":154,"movePct":null,"name":"Double-Edge","totalDmg":null},"evs":[0,0,0,0,0,0]},{"opponent":"Appletun","move":{"category":"special move","defenderName":"Blastoise","defenderHp":154,"movePct":0.78,"name":"Energy Ball","totalDmg":120},"evs":[0,0,0,0,0,0]},{"opponent":"Grapploct","move":{"category":"physical move","defenderName":"Blastoise","defenderHp":154,"movePct":0.61,"name":"Close Combat","totalDmg":94},"evs":[0,0,0,0,0,0]},{"opponent":"Polteageist","move":{"category":"special move","defenderName":"Blastoise","defenderHp":154,"movePct":0.55,"name":"Giga Drain","totalDmg":85},"evs":[0,0,0,0,0,0]},{"opponent":"Hatterene","move":{"category":"special move","defenderName":"Blastoise","defenderHp":154,"movePct":0.66,"name":"Future Sight","totalDmg":101},"evs":[0,0,0,0,0,0]},{"opponent":"Grimmsnarl","move":{"category":"physical move","defenderName":"Blastoise","defenderHp":154,"movePct":0.82,"name":"Power Whip","totalDmg":127},"evs":[0,0,0,0,0,0]},{"opponent":"Perrserker","move":{"category":"physical move","defenderName":"Blastoise","defenderHp":154,"movePct":null,"name":"Double-Edge","totalDmg":null},"evs":[0,0,0,0,0,0]},{"opponent":"Sirfetch'd","move":{"category":"physical move","defenderName":"Blastoise","defenderHp":169,"movePct":0.61,"name":"Leaf Blade","totalDmg":103},"evs":[0,0,0,0,0,0]},{"opponent":"Mr. Rime","move":{"category":"special move","defenderName":"Blastoise","defenderHp":154,"movePct":0.68,"name":"Thunder","totalDmg":104},"evs":[0,0,0,0,0,0]},{"opponent":"Alcremie","move":{"category":"special move","defenderName":"Blastoise","defenderHp":154,"movePct":0.56,"name":"Energy Ball","totalDmg":86},"evs":[0,0,0,0,0,0]},{"opponent":"Pincurchin","move":{"category":"special move","defenderName":"Blastoise","defenderHp":162,"movePct":0.72,"name":"Thunder","totalDmg":116},"evs":[0,0,0,0,0,0]},{"opponent":"Eiscue","move":{"category":"physical move","defenderName":"Blastoise","defenderHp":169,"movePct":null,"name":"Double-Edge","totalDmg":null},"evs":[0,0,0,0,0,0]},{"opponent":"Morpeko","move":{"category":"physical move","defenderName":"Blastoise","defenderHp":158,"movePct":0.81,"name":"Aura Wheel","totalDmg":128},"evs":[0,0,0,0,0,0]},{"opponent":"Cufant","move":{"category":"physical move","defenderName":"Blastoise","defenderHp":154,"movePct":null,"name":"Double-Edge","totalDmg":null},"evs":[0,0,0,0,0,0]},{"opponent":"Copperajah","move":{"category":"physical move","defenderName":"Blastoise","defenderHp":154,"movePct":null,"name":"Double-Edge","totalDmg":null},"evs":[0,0,0,0,0,0]},{"opponent":"Dracozolt","move":{"category":"physical move","defenderName":"Blastoise","defenderHp":154,"movePct":0.81,"name":"Wild Charge","totalDmg":124},"evs":[0,0,0,0,0,0]},{"opponent":"Arctozolt","move":{"category":"special move","defenderName":"Blastoise","defenderHp":154,"movePct":0.86,"name":"Thunder","totalDmg":133},"evs":[0,0,0,0,0,0]},{"opponent":"Dragapult","move":{"category":"special move","defenderName":"Blastoise","defenderHp":154,"movePct":0.62,"name":"Thunder","totalDmg":96},"evs":[0,0,0,0,0,0]},{"opponent":"Zacian","move":{"category":"physical move","defenderName":"Blastoise","defenderHp":154,"movePct":0.67,"name":"Wild Charge","totalDmg":103},"evs":[0,0,0,0,0,0]},{"opponent":"Zamazenta","move":{"category":"physical move","defenderName":"Blastoise","defenderHp":154,"movePct":0.67,"name":"Wild Charge","totalDmg":103},"evs":[0,0,0,0,0,0]},{"opponent":"Eternatus","move":{"category":"special move","defenderName":"Blastoise","defenderHp":154,"movePct":0.55,"name":"Sludge Wave","totalDmg":85},"evs":[83,53,9,136,212,17]}]}